pwm_controller.v
`timescale 1ns / 1ps
module pwm_controller (
    input clk,
    input rst,
    input start,
    output reg pwm_out,
    output reg [2:0] count
);

reg [1:0] PS,NS; //State Registers
parameter [1:0] idle = 2'b00; //Idle State
parameter [1:0] PWM_40 = 2'b01; //PWM 40% State
parameter [1:0] PWM_60 = 2'b10; //PWM 60% State
parameter [1:0] PWM_80 = 2'b11; //PWM 80% State

//State Updation Logic
always @(posedge clk or posedge rst) begin
    if (rst) begin
        PS <= idle; //Reset to Idle State
    end else begin
        PS <= NS; //Update State
    end
end

//Counter Logic
//reg [2:0] count;

//Counter to control the PWM signal 
/*Counter is reset to 0 when rst is high or when count reaches 4.
The counter will count from 0 to 4, 
then reset to 0 therefore here a OR gate is realized to reset the counter when it reaches 4.*/
always @(posedge clk or posedge rst) begin
    if (rst) begin
        count <= 3'b000; //Reset Counter
    end
    else if (count ==4) begin
        count <= 3'b000; //Reset Counter to 0
    end
    else begin
        count <= count + 1; //Increment Counter
    end
end

//State Transistion Logic
/* Asynchronous rst is used and at every state whenever count reached to 4 it will move to the next state*/
always @(start or rst or PS or count) begin
    if(rst) begin
        NS = idle; //Reset to Idle State
    end
    else begin
        case (PS)
            idle: begin
                if (start) begin
                    NS = PWM_40; //Transition to PWM 40% State
                end 
                else begin
                    NS = idle; //Stay in Idle State
                end
            end
            PWM_40: begin
                if (count == 4) begin
                    NS = PWM_60; //Transition to PWM 60% State
                end 
                else begin
                    NS = PWM_40; //Stay in PWM 40% State
                end
            end
            PWM_60: begin
                if (count == 4) begin
                    NS = PWM_80; //Transition to PWM 80% State
                end 
                else begin
                    NS = PWM_60; //Stay in PWM 60% State
                end
            end
            PWM_80: begin
                if (count == 4) begin
                    NS = PWM_40; //Transition to PWM 40% State
                end 
                else begin
                    NS = PWM_80; //Stay in PWM 80% State
                end
            end 
            default: NS = idle; //Default case to Idle State
        endcase
    end
end

//Output Logic

always @(PS or count) begin
    case(PS) 
        idle: begin
            pwm_out = 1'b0; //Output Low in Idle State
        end
        PWM_40: begin
            if (count <= 1) begin
                pwm_out = 1'b1; //Output High for 40% duty cycle
            end 
            else begin
                pwm_out = 1'b0; //Output Low for 60% duty cycle
            end
        end
        PWM_60: begin
            if (count <= 2) begin
                pwm_out = 1'b1; //Output High for 60% duty cycle
            end 
            else begin
                pwm_out = 1'b0; //Output Low for 40% duty cycle
            end
        end
        PWM_80: begin
            if (count <= 3) begin
                pwm_out = 1'b1; //Output High for 80% duty cycle
            end 
            else begin
                pwm_out = 1'b0; //Output Low for 20% duty cycle
            end
        end
    endcase
end


endmodule

pwm_controller_tb.v
`timescale 1ns / 1ps
`include "pwm_controller.v"
module pwm_controller_tb;
reg clk,rst,start;
wire pwm_out;

pwm_controller dut (
    .clk(clk),
    .rst(rst),
    .start(start),
    .pwm_out(pwm_out)
);

// Clock Generation
initial begin
    clk = 1'b0;
    forever #5 clk = ~clk;

end
initial begin
    $dumpfile("pwm_controller.vcd");
    $dumpvars;
    rst = 1'b1;
    #10;
    rst = 1'b0;
    #10;
    start = 1'b1; // Start PWM generation
    #1500 $finish;
end
endmodule

pwm_controller.vcd
$date
	Mon Apr 07 01:37:03 2025
$end
$version
	Icarus Verilog
$end
$timescale
	1ps
$end
$scope module pwm_controller_tb $end
$var wire 1 ! pwm_out $end
$var reg 1 " clk $end
$var reg 1 # rst $end
$var reg 1 $ start $end
$scope module dut $end
$var wire 1 " clk $end
$var wire 1 # rst $end
$var wire 1 $ start $end
$var parameter 2 % PWM_40 $end
$var parameter 2 & PWM_60 $end
$var parameter 2 ' PWM_80 $end
$var parameter 2 ( idle $end
$var reg 2 ) NS [1:0] $end
$var reg 2 * PS [1:0] $end
$var reg 3 + count [2:0] $end
$var reg 1 ! pwm_out $end
$upscope $end
$upscope $end
$enddefinitions $end
$comment Show the parameter values. $end
$dumpall
b0 (
b11 '
b10 &
b1 %
$end
#0
$dumpvars
b0 +
b0 *
b0 )
x$
1#
0"
0!
$end
#5000
1"
#10000
0"
0#
#15000
b1 +
1"
#20000
b1 )
0"
1$
#25000
b10 +
b1 *
1"
#30000
0"
#35000
b11 +
1"
#40000
0"
#45000
b10 )
b100 +
1"
#50000
0"
#55000
1!
b10 *
b0 +
1"
#60000
0"
#65000
b1 +
1"
#70000
0"
#75000
b10 +
1"
#80000
0"
#85000
0!
b11 +
1"
#90000
0"
#95000
b11 )
b100 +
1"
#100000
0"
#105000
1!
b0 +
b11 *
1"
#110000
0"
#115000
b1 +
1"
#120000
0"
#125000
b10 +
1"
#130000
0"
#135000
b11 +
1"
#140000
0"
#145000
0!
b1 )
b100 +
1"
#150000
0"
#155000
1!
b1 *
b0 +
1"
#160000
0"
#165000
b1 +
1"
#170000
0"
#175000
0!
b10 +
1"
#180000
0"
#185000
b11 +
1"
#190000
0"
#195000
b10 )
b100 +
1"
#200000
0"
#205000
1!
b0 +
b10 *
1"
#210000
0"
#215000
b1 +
1"
#220000
0"
#225000
b10 +
1"
#230000
0"
#235000
0!
b11 +
1"
#240000
0"
#245000
b11 )
b100 +
1"
#250000
0"
#255000
1!
b11 *
b0 +
1"
#260000
0"
#265000
b1 +
1"
#270000
0"
#275000
b10 +
1"
#280000
0"
#285000
b11 +
1"
#290000
0"
#295000
0!
b1 )
b100 +
1"
#300000
0"
#305000
1!
b0 +
b1 *
1"
#310000
0"
#315000
b1 +
1"
#320000
0"
#325000
0!
b10 +
1"
#330000
0"
#335000
b11 +
1"
#340000
0"
#345000
b10 )
b100 +
1"
#350000
0"
#355000
1!
b10 *
b0 +
1"
#360000
0"
#365000
b1 +
1"
#370000
0"
#375000
b10 +
1"
#380000
0"
#385000
0!
b11 +
1"
#390000
0"
#395000
b11 )
b100 +
1"
#400000
0"
#405000
1!
b0 +
b11 *
1"
#410000
0"
#415000
b1 +
1"
#420000
0"
#425000
b10 +
1"
#430000
0"
#435000
b11 +
1"
#440000
0"
#445000
0!
b1 )
b100 +
1"
#450000
0"
#455000
1!
b1 *
b0 +
1"
#460000
0"
#465000
b1 +
1"
#470000
0"
#475000
0!
b10 +
1"
#480000
0"
#485000
b11 +
1"
#490000
0"
#495000
b10 )
b100 +
1"
#500000
0"
#505000
1!
b0 +
b10 *
1"
#510000
0"
#515000
b1 +
1"
#520000
0"
#525000
b10 +
1"
#530000
0"
#535000
0!
b11 +
1"
#540000
0"
#545000
b11 )
b100 +
1"
#550000
0"
#555000
1!
b11 *
b0 +
1"
#560000
0"
#565000
b1 +
1"
#570000
0"
#575000
b10 +
1"
#580000
0"
#585000
b11 +
1"
#590000
0"
#595000
0!
b1 )
b100 +
1"
#600000
0"
#605000
1!
b0 +
b1 *
1"
#610000
0"
#615000
b1 +
1"
#620000
0"
#625000
0!
b10 +
1"
#630000
0"
#635000
b11 +
1"
#640000
0"
#645000
b10 )
b100 +
1"
#650000
0"
#655000
1!
b10 *
b0 +
1"
#660000
0"
#665000
b1 +
1"
#670000
0"
#675000
b10 +
1"
#680000
0"
#685000
0!
b11 +
1"
#690000
0"
#695000
b11 )
b100 +
1"
#700000
0"
#705000
1!
b0 +
b11 *
1"
#710000
0"
#715000
b1 +
1"
#720000
0"
#725000
b10 +
1"
#730000
0"
#735000
b11 +
1"
#740000
0"
#745000
0!
b1 )
b100 +
1"
#750000
0"
#755000
1!
b1 *
b0 +
1"
#760000
0"
#765000
b1 +
1"
#770000
0"
#775000
0!
b10 +
1"
#780000
0"
#785000
b11 +
1"
#790000
0"
#795000
b10 )
b100 +
1"
#800000
0"
#805000
1!
b0 +
b10 *
1"
#810000
0"
#815000
b1 +
1"
#820000
0"
#825000
b10 +
1"
#830000
0"
#835000
0!
b11 +
1"
#840000
0"
#845000
b11 )
b100 +
1"
#850000
0"
#855000
1!
b11 *
b0 +
1"
#860000
0"
#865000
b1 +
1"
#870000
0"
#875000
b10 +
1"
#880000
0"
#885000
b11 +
1"
#890000
0"
#895000
0!
b1 )
b100 +
1"
#900000
0"
#905000
1!
b0 +
b1 *
1"
#910000
0"
#915000
b1 +
1"
#920000
0"
#925000
0!
b10 +
1"
#930000
0"
#935000
b11 +
1"
#940000
0"
#945000
b10 )
b100 +
1"
#950000
0"
#955000
1!
b10 *
b0 +
1"
#960000
0"
#965000
b1 +
1"
#970000
0"
#975000
b10 +
1"
#980000
0"
#985000
0!
b11 +
1"
#990000
0"
#995000
b11 )
b100 +
1"
#1000000
0"
#1005000
1!
b0 +
b11 *
1"
#1010000
0"
#1015000
b1 +
1"
#1020000
0"
#1025000
b10 +
1"
#1030000
0"
#1035000
b11 +
1"
#1040000
0"
#1045000
0!
b1 )
b100 +
1"
#1050000
0"
#1055000
1!
b1 *
b0 +
1"
#1060000
0"
#1065000
b1 +
1"
#1070000
0"
#1075000
0!
b10 +
1"
#1080000
0"
#1085000
b11 +
1"
#1090000
0"
#1095000
b10 )
b100 +
1"
#1100000
0"
#1105000
1!
b0 +
b10 *
1"
#1110000
0"
#1115000
b1 +
1"
#1120000
0"
#1125000
b10 +
1"
#1130000
0"
#1135000
0!
b11 +
1"
#1140000
0"
#1145000
b11 )
b100 +
1"
#1150000
0"
#1155000
1!
b11 *
b0 +
1"
#1160000
0"
#1165000
b1 +
1"
#1170000
0"
#1175000
b10 +
1"
#1180000
0"
#1185000
b11 +
1"
#1190000
0"
#1195000
0!
b1 )
b100 +
1"
#1200000
0"
#1205000
1!
b0 +
b1 *
1"
#1210000
0"
#1215000
b1 +
1"
#1220000
0"
#1225000
0!
b10 +
1"
#1230000
0"
#1235000
b11 +
1"
#1240000
0"
#1245000
b10 )
b100 +
1"
#1250000
0"
#1255000
1!
b10 *
b0 +
1"
#1260000
0"
#1265000
b1 +
1"
#1270000
0"
#1275000
b10 +
1"
#1280000
0"
#1285000
0!
b11 +
1"
#1290000
0"
#1295000
b11 )
b100 +
1"
#1300000
0"
#1305000
1!
b0 +
b11 *
1"
#1310000
0"
#1315000
b1 +
1"
#1320000
0"
#1325000
b10 +
1"
#1330000
0"
#1335000
b11 +
1"
#1340000
0"
#1345000
0!
b1 )
b100 +
1"
#1350000
0"
#1355000
1!
b1 *
b0 +
1"
#1360000
0"
#1365000
b1 +
1"
#1370000
0"
#1375000
0!
b10 +
1"
#1380000
0"
#1385000
b11 +
1"
#1390000
0"
#1395000
b10 )
b100 +
1"
#1400000
0"
#1405000
1!
b0 +
b10 *
1"
#1410000
0"
#1415000
b1 +
1"
#1420000
0"
#1425000
b10 +
1"
#1430000
0"
#1435000
0!
b11 +
1"
#1440000
0"
#1445000
b11 )
b100 +
1"
#1450000
0"
#1455000
1!
b11 *
b0 +
1"
#1460000
0"
#1465000
b1 +
1"
#1470000
0"
#1475000
b10 +
1"
#1480000
0"
#1485000
b11 +
1"
#1490000
0"
#1495000
0!
b1 )
b100 +
1"
#1500000
0"
#1505000
1!
b0 +
b1 *
1"
#1510000
0"
#1515000
b1 +
1"
